surquest/utils/config/__init__.py
surquest/utils/config/formatter.py
surquest_utils_config_formatter-0.0.2.dist-info/METADATA
surquest_utils_config_formatter-0.0.2.dist-info/WHEEL
surquest_utils_config_formatter-0.0.2.dist-info/licenses/LICENSE
surquest_utils_config_formatter-0.0.2.dist-info/RECORD
