Metadata-Version: 2.1
Name: surquest-utils-config-formatter
Version: 0.0.2
Summary: ConfigFormatter helps you to follow the naming patterns of Google Cloud resources in your Python application.
Project-URL: Homepage, https://github.com/surquest/python-utils-loader
Project-URL: Bug Tracker, https://github.com/surquest/python-utils-loader/issues
Author-email: Michal Švarc <michal.svarc@surquest.com>
License-File: LICENSE
Classifier: License :: OSI Approved :: MIT License
Classifier: Programming Language :: Python :: 3
Provides-Extra: test
Requires-Dist: pytest-cov>=4.0.0; extra == 'test'
Requires-Dist: pytest>=7.2.1; extra == 'test'
